switchbee/__init__.py
switchbee/const.py
switchbee/py.typed
switchbee/utils.py
switchbee/api/__init__.py
switchbee/api/central_unit.py
switchbee/api/polling.py
switchbee/api/wsrpc.py
switchbee/central_unit/__init__.py
switchbee/device/__init__.py
pyswitchbee-1.8.2.dist-info/LICENSE
pyswitchbee-1.8.2.dist-info/METADATA
pyswitchbee-1.8.2.dist-info/WHEEL
pyswitchbee-1.8.2.dist-info/top_level.txt
pyswitchbee-1.8.2.dist-info/RECORD
