Metadata-Version: 2.1
Name: pyswitchbee
Version: 1.8.2
Summary: SwitchBee Python Integration.
Author-email: Jafar Atili <at.jafar@outlook.com>
Project-URL: homepage, https://pypi.org/project/pyswitchbee/
Project-URL: repository, https://github.com/jafar-atili/pySwitchbee/
Keywords: home,automation,switchbee,smart
Classifier: Intended Audience :: Developers
Classifier: Operating System :: OS Independent
Classifier: Topic :: Home Automation
Classifier: Topic :: Software Development :: Libraries :: Python Modules
Classifier: Typing :: Typed
Classifier: License :: OSI Approved :: Apache Software License
Requires-Python: >=3.9
License-File: LICENSE
Requires-Dist: aiohttp
Requires-Dist: awesomeversion
